{
	"id": "be742ed5-227f-4a25-8737-0d4efc82382a",
	"values": [
		{
			"key": "URL_API_VERSION_V1",
			"value": "api/v1",
			"type": "default",
			"enabled": true
		},
		{
			"key": "AUTHENTICATION_URL",
			"value": "{{ENVIRONMENT_ORIGIN}}:{{AUTHENTICATION_API_PORT}}/{{URL_API_VERSION_V1}}/{{AUTHENTICATION_API_PREFIX}}",
			"type": "default",
			"enabled": true
		},
		{
			"key": "PRODUCT_URL",
			"value": "{{ENVIRONMENT_ORIGIN}}:{{PRODUCT_API_PORT}}/{{URL_API_VERSION_V1}}/{{PRODUCT_API_PREFIX}}",
			"type": "default",
			"enabled": true
		},
		{
			"key": "BASKET_URL",
			"value": "{{ENVIRONMENT_ORIGIN}}:{{BASKET_API_PORT}}/{{URL_API_VERSION_V1}}/{{BASKET_API_PREFIX}}",
			"type": "default",
			"enabled": true
		},
		{
			"key": "DISCOUNT_URL",
			"value": "{{ENVIRONMENT_ORIGIN}}:{{DISCOUNT_API_PORT}}/{{URL_API_VERSION_V1}}/{{DISCOUNT_API_PREFIX}}",
			"type": "default",
			"enabled": true
		},
		{
			"key": "ORDER_URL",
			"value": "{{ENVIRONMENT_ORIGIN}}:{{ORDER_API_PORT}}/{{URL_API_VERSION_V1}}/{{ORDER_API_PREFIX}}",
			"type": "default",
			"enabled": true
		},
		{
			"key": "PRODUCT_URL_OCELOT_GATEWAY",
			"value": "{{ENVIRONMENT_ORIGIN}}:{{OCELOT_API_PORT}}",
			"type": "default",
			"enabled": true
		},
		{
			"key": "BASKET_URL_OCELOT_GATEWAY",
			"value": "{{ENVIRONMENT_ORIGIN}}:{{OCELOT_API_PORT}}",
			"type": "default",
			"enabled": true
		},
		{
			"key": "DISCOUNT_URL_OCELOT_GATEWAY",
			"value": "{{ENVIRONMENT_ORIGIN}}:{{OCELOT_API_PORT}}",
			"type": "default",
			"enabled": true
		},
		{
			"key": "ORDER_URL_OCELOT_GATEWAY",
			"value": "{{ENVIRONMENT_ORIGIN}}:{{OCELOT_API_PORT}}",
			"type": "default",
			"enabled": true
		},
		{
			"key": "SHOPPING_AGGREGATOR_URL",
			"value": "{{ENVIRONMENT_ORIGIN}}:{{SHOPPING_AGGREGATOR_PORT}}/{{URL_API_VERSION_V1}}/{{SHOPPING_AGGREGATOR_API_PREFIX}}",
			"type": "default",
			"enabled": true
		}
	],
	"name": "Globals",
	"_postman_variable_scope": "globals",
	"_postman_exported_at": "2023-12-11T13:11:08.111Z",
	"_postman_exported_using": "Postman/10.20.10"
}